.pypirc
CHANGES.txt
MANIFEST.in
README.txt
distribute-0.6.24.tar.gz
setup.py
p4a/__init__.py
p4a.ploneevent.egg-info/PKG-INFO
p4a.ploneevent.egg-info/SOURCES.txt
p4a.ploneevent.egg-info/dependency_links.txt
p4a.ploneevent.egg-info/entry_points.txt
p4a.ploneevent.egg-info/namespace_packages.txt
p4a.ploneevent.egg-info/not-zip-safe
p4a.ploneevent.egg-info/requires.txt
p4a.ploneevent.egg-info/top_level.txt
p4a/ploneevent/__init__.py
p4a/ploneevent/configure.zcml
p4a/ploneevent/interfaces.py
p4a/ploneevent/monkeys.py
p4a/ploneevent/rebuild_pot.sh
p4a/ploneevent/schemaextender.py
p4a/ploneevent/sitesetup.py
p4a/ploneevent/i18n/p4a.plonevent-Plone-de.po
p4a/ploneevent/i18n/p4a.plonevent-Plone-en.po
p4a/ploneevent/i18n/p4a.plonevent-Plone-es.po
p4a/ploneevent/i18n/p4a.plonevent-Plone-no.po
p4a/ploneevent/i18n/p4a.plonevent-Plone-sv.po
p4a/ploneevent/locales/p4a.ploneevent.pot
p4a/ploneevent/locales/de/LC_MESSAGES/p4a.ploneevent.po
p4a/ploneevent/locales/en/LC_MESSAGES/p4a.ploneevent.mo
p4a/ploneevent/locales/en/LC_MESSAGES/p4a.ploneevent.po
p4a/ploneevent/locales/es/LC_MESSAGES/p4a.ploneevent.mo
p4a/ploneevent/locales/es/LC_MESSAGES/p4a.ploneevent.po
p4a/ploneevent/locales/no/LC_MESSAGES/p4a.ploneevent.mo
p4a/ploneevent/locales/no/LC_MESSAGES/p4a.ploneevent.po
p4a/ploneevent/locales/sv/LC_MESSAGES/p4a.ploneevent.mo
p4a/ploneevent/locales/sv/LC_MESSAGES/p4a.ploneevent.po
p4a/ploneevent/profiles/default/catalog.xml
p4a/ploneevent/recurrence/__init__.py
p4a/ploneevent/recurrence/configure.zcml
p4a/ploneevent/recurrence/indexing.py
p4a/ploneevent/recurrence/interfaces.py
p4a/ploneevent/recurrence/recurrence.py
p4a/ploneevent/recurrence/schemaextender.py
p4a/ploneevent/recurrence/tests.py
p4a/ploneevent/recurrence/browser/__init__.py
p4a/ploneevent/recurrence/browser/configure.zcml
p4a/ploneevent/recurrence/browser/event_view.pt
p4a/ploneevent/recurrence/browser/event_view.py
p4a/ploneevent/recurrence/browser/ui.kss