Metadata-Version: 1.0
Name: p4a.ploneevent
Version: 0.7.4
Summary: Plone4Artists event extensions for Plone
Home-page: http://pypi.python.org/pypi/p4a.ploneevent/
Author: Lennart Regebro
Author-email: regebro@gmail.com
License: GPL
Keywords: Plone4Artists recurring events calendar calendaring
Platform: UNKNOWN
Classifier: Framework :: Zope2
Classifier: Framework :: Zope3
Classifier: Framework :: Plone
Classifier: Programming Language :: Python
Classifier: License :: OSI Approved :: GNU General Public License (GPL)
Classifier: Topic :: Software Development :: Libraries :: Python Modules
